<?xml version="1.0" encoding="UTF-8" ?>
<!DOCTYPE mapper PUBLIC "-//mybatis.org//DTD Mapper 3.0//EN" "http://mybatis.org/dtd/mybatis-3-mapper.dtd" >
<mapper namespace="com.kf.data.mybatis.mapper.PdfCodeTableMapper" >
  <resultMap id="BaseResultMap" type="com.kf.data.mybatis.entity.PdfCodeTable" >
    <!--
      WARNING - @mbggenerated
      This element is automatically generated by MyBatis Generator, do not modify.
      This element was generated on Mon Sep 18 16:39:19 CST 2017.
    -->
    <id column="id" property="id" jdbcType="INTEGER" />
    <result column="pdf_type" property="pdfType" jdbcType="VARCHAR" />
    <result column="table_name" property="tableName" jdbcType="VARCHAR" />
    <result column="task" property="task" jdbcType="INTEGER" />
  </resultMap>
  <sql id="Example_Where_Clause" >
    <!--
      WARNING - @mbggenerated
      This element is automatically generated by MyBatis Generator, do not modify.
      This element was generated on Mon Sep 18 16:39:19 CST 2017.
    -->
    <where >
      <foreach collection="oredCriteria" item="criteria" separator="or" >
        <if test="criteria.valid" >
          <trim prefix="(" suffix=")" prefixOverrides="and" >
            <foreach collection="criteria.criteria" item="criterion" >
              <choose >
                <when test="criterion.noValue" >
                  and ${criterion.condition}
                </when>
                <when test="criterion.singleValue" >
                  and ${criterion.condition} #{criterion.value}
                </when>
                <when test="criterion.betweenValue" >
                  and ${criterion.condition} #{criterion.value} and #{criterion.secondValue}
                </when>
                <when test="criterion.listValue" >
                  and ${criterion.condition}
                  <foreach collection="criterion.value" item="listItem" open="(" close=")" separator="," >
                    #{listItem}
                  </foreach>
                </when>
              </choose>
            </foreach>
          </trim>
        </if>
      </foreach>
    </where>
  </sql>
  <sql id="Update_By_Example_Where_Clause" >
    <!--
      WARNING - @mbggenerated
      This element is automatically generated by MyBatis Generator, do not modify.
      This element was generated on Mon Sep 18 16:39:19 CST 2017.
    -->
    <where >
      <foreach collection="example.oredCriteria" item="criteria" separator="or" >
        <if test="criteria.valid" >
          <trim prefix="(" suffix=")" prefixOverrides="and" >
            <foreach collection="criteria.criteria" item="criterion" >
              <choose >
                <when test="criterion.noValue" >
                  and ${criterion.condition}
                </when>
                <when test="criterion.singleValue" >
                  and ${criterion.condition} #{criterion.value}
                </when>
                <when test="criterion.betweenValue" >
                  and ${criterion.condition} #{criterion.value} and #{criterion.secondValue}
                </when>
                <when test="criterion.listValue" >
                  and ${criterion.condition}
                  <foreach collection="criterion.value" item="listItem" open="(" close=")" separator="," >
                    #{listItem}
                  </foreach>
                </when>
              </choose>
            </foreach>
          </trim>
        </if>
      </foreach>
    </where>
  </sql>
  <sql id="Base_Column_List" >
    <!--
      WARNING - @mbggenerated
      This element is automatically generated by MyBatis Generator, do not modify.
      This element was generated on Mon Sep 18 16:39:19 CST 2017.
    -->
    id, pdf_type, `table_name`, task
  </sql>
  <select id="selectByExample" resultMap="BaseResultMap" parameterType="com.kf.data.mybatis.entity.PdfCodeTableExample" >
    <!--
      WARNING - @mbggenerated
      This element is automatically generated by MyBatis Generator, do not modify.
      This element was generated on Mon Sep 18 16:39:19 CST 2017.
    -->
    select
    <if test="distinct" >
      distinct
    </if>
    <include refid="Base_Column_List" />
    from pdf_code_table
    <if test="_parameter != null" >
      <include refid="Example_Where_Clause" />
    </if>
    <if test="orderByClause != null" >
      order by ${orderByClause}
    </if>
  </select>
  <select id="selectByPrimaryKey" resultMap="BaseResultMap" parameterType="java.lang.Integer" >
    <!--
      WARNING - @mbggenerated
      This element is automatically generated by MyBatis Generator, do not modify.
      This element was generated on Mon Sep 18 16:39:19 CST 2017.
    -->
    select 
    <include refid="Base_Column_List" />
    from pdf_code_table
    where id = #{id,jdbcType=INTEGER}
  </select>
  <delete id="deleteByPrimaryKey" parameterType="java.lang.Integer" >
    <!--
      WARNING - @mbggenerated
      This element is automatically generated by MyBatis Generator, do not modify.
      This element was generated on Mon Sep 18 16:39:19 CST 2017.
    -->
    delete from pdf_code_table
    where id = #{id,jdbcType=INTEGER}
  </delete>
  <delete id="deleteByExample" parameterType="com.kf.data.mybatis.entity.PdfCodeTableExample" >
    <!--
      WARNING - @mbggenerated
      This element is automatically generated by MyBatis Generator, do not modify.
      This element was generated on Mon Sep 18 16:39:19 CST 2017.
    -->
    delete from pdf_code_table
    <if test="_parameter != null" >
      <include refid="Example_Where_Clause" />
    </if>
  </delete>
  <insert id="insert" parameterType="com.kf.data.mybatis.entity.PdfCodeTable" >
    <!--
      WARNING - @mbggenerated
      This element is automatically generated by MyBatis Generator, do not modify.
      This element was generated on Mon Sep 18 16:39:19 CST 2017.
    -->
    <selectKey resultType="java.lang.Integer" keyProperty="id" order="AFTER" >
      SELECT LAST_INSERT_ID()
    </selectKey>
    insert into pdf_code_table (pdf_type, `table_name`, task
      )
    values (#{pdfType,jdbcType=VARCHAR}, #{tableName,jdbcType=VARCHAR}, #{task,jdbcType=INTEGER}
      )
  </insert>
  <insert id="insertSelective" parameterType="com.kf.data.mybatis.entity.PdfCodeTable" >
    <!--
      WARNING - @mbggenerated
      This element is automatically generated by MyBatis Generator, do not modify.
      This element was generated on Mon Sep 18 16:39:19 CST 2017.
    -->
    <selectKey resultType="java.lang.Integer" keyProperty="id" order="AFTER" >
      SELECT LAST_INSERT_ID()
    </selectKey>
    insert into pdf_code_table
    <trim prefix="(" suffix=")" suffixOverrides="," >
      <if test="pdfType != null" >
        pdf_type,
      </if>
      <if test="tableName != null" >
        `table_name`,
      </if>
      <if test="task != null" >
        task,
      </if>
    </trim>
    <trim prefix="values (" suffix=")" suffixOverrides="," >
      <if test="pdfType != null" >
        #{pdfType,jdbcType=VARCHAR},
      </if>
      <if test="tableName != null" >
        #{tableName,jdbcType=VARCHAR},
      </if>
      <if test="task != null" >
        #{task,jdbcType=INTEGER},
      </if>
    </trim>
  </insert>
  <select id="countByExample" parameterType="com.kf.data.mybatis.entity.PdfCodeTableExample" resultType="java.lang.Integer" >
    <!--
      WARNING - @mbggenerated
      This element is automatically generated by MyBatis Generator, do not modify.
      This element was generated on Mon Sep 18 16:39:19 CST 2017.
    -->
    select count(*) from pdf_code_table
    <if test="_parameter != null" >
      <include refid="Example_Where_Clause" />
    </if>
  </select>
  <update id="updateByExampleSelective" parameterType="map" >
    <!--
      WARNING - @mbggenerated
      This element is automatically generated by MyBatis Generator, do not modify.
      This element was generated on Mon Sep 18 16:39:19 CST 2017.
    -->
    update pdf_code_table
    <set >
      <if test="record.id != null" >
        id = #{record.id,jdbcType=INTEGER},
      </if>
      <if test="record.pdfType != null" >
        pdf_type = #{record.pdfType,jdbcType=VARCHAR},
      </if>
      <if test="record.tableName != null" >
        `table_name` = #{record.tableName,jdbcType=VARCHAR},
      </if>
      <if test="record.task != null" >
        task = #{record.task,jdbcType=INTEGER},
      </if>
    </set>
    <if test="_parameter != null" >
      <include refid="Update_By_Example_Where_Clause" />
    </if>
  </update>
  <update id="updateByExample" parameterType="map" >
    <!--
      WARNING - @mbggenerated
      This element is automatically generated by MyBatis Generator, do not modify.
      This element was generated on Mon Sep 18 16:39:19 CST 2017.
    -->
    update pdf_code_table
    set id = #{record.id,jdbcType=INTEGER},
      pdf_type = #{record.pdfType,jdbcType=VARCHAR},
      `table_name` = #{record.tableName,jdbcType=VARCHAR},
      task = #{record.task,jdbcType=INTEGER}
    <if test="_parameter != null" >
      <include refid="Update_By_Example_Where_Clause" />
    </if>
  </update>
  <update id="updateByPrimaryKeySelective" parameterType="com.kf.data.mybatis.entity.PdfCodeTable" >
    <!--
      WARNING - @mbggenerated
      This element is automatically generated by MyBatis Generator, do not modify.
      This element was generated on Mon Sep 18 16:39:19 CST 2017.
    -->
    update pdf_code_table
    <set >
      <if test="pdfType != null" >
        pdf_type = #{pdfType,jdbcType=VARCHAR},
      </if>
      <if test="tableName != null" >
        `table_name` = #{tableName,jdbcType=VARCHAR},
      </if>
      <if test="task != null" >
        task = #{task,jdbcType=INTEGER},
      </if>
    </set>
    where id = #{id,jdbcType=INTEGER}
  </update>
  <update id="updateByPrimaryKey" parameterType="com.kf.data.mybatis.entity.PdfCodeTable" >
    <!--
      WARNING - @mbggenerated
      This element is automatically generated by MyBatis Generator, do not modify.
      This element was generated on Mon Sep 18 16:39:19 CST 2017.
    -->
    update pdf_code_table
    set pdf_type = #{pdfType,jdbcType=VARCHAR},
      `table_name` = #{tableName,jdbcType=VARCHAR},
      task = #{task,jdbcType=INTEGER}
    where id = #{id,jdbcType=INTEGER}
  </update>
</mapper>